django_payfast-0.3.dist-info/METADATA
django_payfast-0.3.dist-info/RECORD
django_payfast-0.3.dist-info/WHEEL
django_payfast-0.3.dist-info/top_level.txt
payfast/__init__.py
payfast/admin.py
payfast/api.py
payfast/conf.py
payfast/forms.py
payfast/models.py
payfast/readable_models.py
payfast/signals.py
payfast/tests.py
payfast/urls.py
payfast/views.py
payfast/migrations/0001_initial.py
payfast/migrations/0002_update_payfastorder_timestamp_fields.py
payfast/migrations/0003_update_payfastorder_m_payment_id.py
payfast/migrations/__init__.py
