Metadata-Version: 2.1
Name: django-payfast
Version: 0.3
Summary: A pluggable Django application for integrating payfast.co.za payment system.
Home-page: https://github.com/pjdelport/django-payfast
Maintainer: Pi Delport
Maintainer-email: pjdelport@gmail.com
License: MIT license
Platform: UNKNOWN
Classifier: Development Status :: 3 - Alpha
Classifier: Environment :: Web Environment
Classifier: Framework :: Django
Classifier: Intended Audience :: Developers
Classifier: License :: OSI Approved :: MIT License
Classifier: Programming Language :: Python :: 2
Classifier: Programming Language :: Python :: 3
Classifier: Topic :: Software Development :: Libraries :: Python Modules
Requires-Dist: six
Requires-Dist: Django
Requires-Dist: ipaddress
Requires-Dist: typing; python_version < "3.5"
